{"total":10,"rows":[
	{"id":"1","dealer_name":"经销商","download_time":"2017-09-01 12:21:22"},
	{"id":"2","dealer_name":"经销商","download_time":"2017-09-01 12:21:22"},
	{"id":"3","dealer_name":"经销商","download_time":"2017-09-01 12:21:22"},
	{"id":"4","dealer_name":"经销商","download_time":"2017-09-01 12:21:22"},
	{"id":"5","dealer_name":"经销商","download_time":"2017-09-01 12:21:22"},
	{"id":"6","dealer_name":"经销商","download_time":"2017-09-01 12:21:22"},
	{"id":"7","dealer_name":"经销商","download_time":"2017-09-01 12:21:22"},
	{"id":"8","dealer_name":"经销商","download_time":"2017-09-01 12:21:22"},
	{"id":"9","dealer_name":"经销商","download_time":"2017-09-01 12:21:22"},
	{"id":"10","dealer_name":"经销商","download_time":"2017-09-01 12:21:22"}
]}
